cifscloak/__init__.py
cifscloak/cifscloak.py
cifscloak-1.0.34.dist-info/LICENSE
cifscloak-1.0.34.dist-info/METADATA
cifscloak-1.0.34.dist-info/WHEEL
cifscloak-1.0.34.dist-info/entry_points.txt
cifscloak-1.0.34.dist-info/top_level.txt
cifscloak-1.0.34.dist-info/RECORD
