Metadata-Version: 2.1
Name: cifscloak
Version: 1.0.34
Summary: Mount cifs shares using encrypted passwords
Home-page: https://github.com/sudoofus/cifscloak
Author: Darren Chambers
Author-email: dazchambers@gmail.com
License: UNKNOWN
Platform: UNKNOWN
License-File: LICENSE
Requires-Dist: cryptography
Requires-Dist: argparse
Requires-Dist: pexpect
Requires-Dist: regex
